[
  {
    "model": "crm.mproduct",
    "pk": 1,
    "fields": {
      "name": "シャンパンA",
      "price": 500,
      "category": 1,
      "tax": 6,
      "tax_price": 650
    }
  },
  {
    "model": "crm.mproduct",
    "pk": 2,
    "fields": {
      "name": "ワインA",
      "price": 500,
      "category": 2,
      "tax": 6,
      "tax_price": 650
    }
  },
  {
    "model": "crm.mproduct",
    "pk": 3,
    "fields": {
      "name": "焼酎A",
      "price": 1000,
      "category": 3,
      "tax": 6,
      "tax_price": 1300
    }
  },
  {
    "model": "crm.mproduct",
    "pk": 4,
    "fields": {
      "name": "サワーA",
      "price": 500,
      "category": 4,
      "tax": 6,
      "tax_price": 650
    }
  },
  {
    "model": "crm.mproduct",
    "pk": 5,
    "fields": {
      "name": "カクテルA",
      "price": 500,
      "category": 5,
      "tax": 6,
      "tax_price": 650
    }
  },
  {
    "model": "crm.mproduct",
    "pk": 6,
    "fields": {
      "name": "日本酒A",
      "price": 1000,
      "category": 6,
      "tax": 6,
      "tax_price": 1300
    }
  },
  {
    "model": "crm.mproduct",
    "pk": 7,
    "fields": {
      "name": "シャンパンB",
      "price": 2000,
      "category": 1,
      "tax": 6,
      "tax_price": 2600
    }
  },
  {
    "model": "crm.mproduct",
    "pk": 8,
    "fields": {
      "name": "シャンパンC",
      "price": 3000,
      "category": 1,
      "tax": 6,
      "tax_price": 3900
    }
  },
  {
    "model": "crm.mproduct",
    "pk": 9,
    "fields": {
      "name": "シャンパンD",
      "price": 3000,
      "category": 1,
      "tax": 6,
      "tax_price": 3900
    }
  },
  {
    "model": "crm.mproduct",
    "pk": 10,
    "fields": {
      "name": "シャンパンE",
      "price": 10000,
      "category": 1,
      "tax": 6,
      "tax_price": 13000
    }
  },
  {
    "model": "crm.mproduct",
    "pk": 11,
    "fields": {
      "name": "ソフトドリンクA",
      "price": 500,
      "category": 9,
      "tax": 6,
      "tax_price": 650
    }
  },
  {
    "model": "crm.mproduct",
    "pk": 12,
    "fields": {
      "name": "ノンアルA",
      "price": 1000,
      "category": 8,
      "tax": 6,
      "tax_price": 1300
    }
  },
  {
    "model": "crm.mproduct",
    "pk": 13,
    "fields": {
      "name": "スイーツA",
      "price": 1000,
      "category": 13,
      "tax": 6,
      "tax_price": 1300
    }
  }
]
